{"stats":{"minecraft:used":{"minecraft:netherite_axe":10},"minecraft:custom":{"minecraft:jump":6,"minecraft:open_chest":1,"minecraft:time_since_rest":1939,"minecraft:damage_dealt":1000,"minecraft:crouch_one_cm":65,"minecraft:sprint_one_cm":438,"minecraft:play_time":1939,"minecraft:time_since_death":1939,"minecraft:walk_one_cm":3557,"minecraft:sneak_time":161,"minecraft:total_world_time":1939,"minecraft:mob_kills":1,"minecraft:drop":2,"minecraft:fly_one_cm":60128},"minecraft:dropped":{"minecraft:iron_ingot":5,"minecraft:poppy":2},"minecraft:picked_up":{"minecraft:iron_ingot":5,"minecraft:poppy":2},"minecraft:killed":{"minecraft:iron_golem":1}},"DataVersion":3465}